deepair_dev_utils/__init__.py
deepair_dev_utils/general/__init__.py
deepair_dev_utils/general/decorators.py
deepair_dev_utils/general/tools.py
deepair_dev_utils/loader/__init__.py
deepair_dev_utils/loader/tools.py
deepair_dev_utils-0.0.7.dist-info/METADATA
deepair_dev_utils-0.0.7.dist-info/RECORD
deepair_dev_utils-0.0.7.dist-info/WHEEL
deepair_dev_utils-0.0.7.dist-info/top_level.txt
