Metadata-Version: 2.1
Name: deepair-dev-utils
Version: 0.0.7
Summary: This is a sub modular package for developer utilities
Home-page: https://bitbucket.org/deepair/
Author: DeepAir Dev
Author-email: naman@deepair.io
License: UNKNOWN
Platform: UNKNOWN
Classifier: Intended Audience :: Developers
Classifier: Programming Language :: Python :: 3
Classifier: License :: OSI Approved :: MIT License
Classifier: Operating System :: OS Independent
